{
  "main": {
    "id": "a7637addfbc265f0",
    "type": "split",
    "children": [
      {
        "id": "994c5c6b76b69cee",
        "type": "tabs",
        "children": [
          {
            "id": "58cd70c1baa2ed89",
            "type": "leaf",
            "state": {
              "type": "pdf",
              "state": {
                "file": "MCA_2024-2026/sql/pdf/Adv DBMS-Unit 2.pdf",
                "page": 1,
                "left": -29,
                "top": 544,
                "zoom": 0.55
              },
              "icon": "lucide-file-text",
              "title": "Adv DBMS-Unit 2"
            }
          }
        ]
      }
    ],
    "direction": "vertical"
  },
  "left": {
    "id": "06a41f721a485662",
    "type": "split",
    "children": [
      {
        "id": "c2db0d9f6a556e67",
        "type": "tabs",
        "children": [
          {
            "id": "22cb213078b520f9",
            "type": "leaf",
            "state": {
              "type": "file-explorer",
              "state": {
                "sortOrder": "alphabetical"
              },
              "icon": "lucide-folder-closed",
              "title": "Files"
            }
          },
          {
            "id": "16624908be184980",
            "type": "leaf",
            "state": {
              "type": "search",
              "state": {
                "query": "",
                "matchingCase": false,
                "explainSearch": false,
                "collapseAll": false,
                "extraContext": false,
                "sortOrder": "alphabetical"
              },
              "icon": "lucide-search",
              "title": "Search"
            }
          },
          {
            "id": "133040de0623604e",
            "type": "leaf",
            "state": {
              "type": "bookmarks",
              "state": {},
              "icon": "lucide-bookmark",
              "title": "Bookmarks"
            }
          }
        ]
      }
    ],
    "direction": "horizontal",
    "width": 260.5026054382324,
    "collapsed": true
  },
  "right": {
    "id": "a7afa5ab8a0baa9e",
    "type": "split",
    "children": [
      {
        "id": "59ca0f4145647ea9",
        "type": "tabs",
        "children": [
          {
            "id": "33fffcad83a145e7",
            "type": "leaf",
            "state": {
              "type": "backlink",
              "state": {
                "file": "Python Data Structures and Algorithms.md",
                "collapseAll": false,
                "extraContext": false,
                "sortOrder": "alphabetical",
                "showSearch": false,
                "searchQuery": "",
                "backlinkCollapsed": false,
                "unlinkedCollapsed": true
              },
              "icon": "links-coming-in",
              "title": "Backlinks for Python Data Structures and Algorithms"
            }
          },
          {
            "id": "1544fcf012f01894",
            "type": "leaf",
            "state": {
              "type": "outgoing-link",
              "state": {
                "file": "Python Data Structures and Algorithms.md",
                "linksCollapsed": false,
                "unlinkedCollapsed": true
              },
              "icon": "links-going-out",
              "title": "Outgoing links from Python Data Structures and Algorithms"
            }
          },
          {
            "id": "3435af2ee3e8649c",
            "type": "leaf",
            "state": {
              "type": "tag",
              "state": {
                "sortOrder": "frequency",
                "useHierarchy": true
              },
              "icon": "lucide-tags",
              "title": "Tags"
            }
          },
          {
            "id": "d8673282661a59c3",
            "type": "leaf",
            "state": {
              "type": "outline",
              "state": {
                "file": "Python Data Structures and Algorithms.md"
              },
              "icon": "lucide-list",
              "title": "Outline of Python Data Structures and Algorithms"
            }
          },
          {
            "id": "728181021839c259",
            "type": "leaf",
            "state": {
              "type": "git-view",
              "state": {},
              "icon": "lucide-file",
              "title": "Plugin no longer active"
            }
          }
        ],
        "currentTab": 4
      }
    ],
    "direction": "horizontal",
    "width": 200,
    "collapsed": true
  },
  "left-ribbon": {
    "hiddenItems": {
      "switcher:Open quick switcher": false,
      "graph:Open graph view": false,
      "canvas:Create new canvas": false,
      "daily-notes:Open today's daily note": false,
      "templates:Insert template": false,
      "command-palette:Open command palette": false,
      "obsidian-git:Open Git source control": false,
      "pdf-plus:PDF++: Toggle auto-copy": false,
      "pdf-plus:PDF++: Toggle auto-focus": false,
      "pdf-plus:PDF++: Toggle auto-paste": false,
      "obsidian-extract-pdf-highlights:PDF Highlights": false,
      "whisper:Open recording controls": false,
      "obsidian-excalidraw-plugin:Create new drawing": false
    }
  },
  "active": "58cd70c1baa2ed89",
  "lastOpenFiles": [
    "MCA_2024-2026/sql/pdf/Adv DBMS-Unit 2 note.md",
    "MCA_2024-2026/sql/pdf/Adv DBMS-Unit 2.pdf",
    "MCA_2024-2026/os/unit 3/Process Subsystem.pdf",
    "MCA_2024-2026/sql/pdf/Adv DBMS-Unit 3.pdf",
    "hacker rank questions.md",
    "dm-lab notes.md",
    "MCA_2024-2026/practice_mcq/c MCQs.md",
    "MCA_2024-2026/DS/lab/c_prog/lab_sheet_6/cll.md",
    "MCA_2024-2026/DS/lab/c_prog/lab_sheet_6/cdll.md",
    "MCA_2024-2026/DS/ds_note/20241123_194027498.pdf",
    "MCA_2024-2026/DS/lab/c_prog/lab_sheet_6",
    "MCA_2024-2026/DS/lab/c_prog/lab_sheet_6/Stack.md",
    "MCA_2024-2026/DS/lab/c_prog/lab_sheet_6/Stack and queue 1.md",
    "MCA_2024-2026/os/Lecture_notes/2024-08-22 05.37.59.excalidraw.md",
    "MCA_2024-2026/os/2024-08-22.md",
    "MCA_2024-2026/os/Untitled.md",
    "MCA_2024-2026/sql/unit1.md",
    "MCA_2024-2026/sql/lab_sheet/SQL_LAB_SHEET_1.md",
    "Highlights for OOP Using JAVA-EXCEPTIONS.md",
    "Highlights for 1. OOP Using JAVA-Introduction.md",
    "JAVA LAB PROGRAMS - 1.pdf",
    "MCA_2024-2026/sql/lab_sheet/SQL_LAB_SHEET_2.md",
    "MCA_2024-2026/sql/lab_sheet",
    "To do list OS.md",
    "Unit 2.md",
    "MCA_2024-2026/sql/Transaction and ACID properties.md",
    "MCA_2024-2026/sql/Unit-2Parallel Databases.md",
    "MCA_2024-2026/sql/Parallel Database.md",
    "MCA_2024-2026/sql/CORE.md",
    "MCA_2024-2026/sql/pdf/Adv DBMS-Unit 5.pdf",
    "MCA_2024-2026/sql/Distributed Database.md",
    "MCA_2024-2026/sql/pdf/Adv DBMS-Unit 4.pdf",
    "MCA_2024-2026/sql/Syllabus.jpeg",
    "Adv DBMS.md",
    "java exam.md",
    "MCA_2024-2026/DS/ds_note",
    "6127394224048553043.jpg",
    "MCA_2024-2026/java/pasted_images/Pasted image 20241001123127.png",
    "MCA_2024-2026/java/pasted_images/Multilevel-Inheritance-in-Java-1.jpg.webp",
    "MCA_2024-2026/java/pasted_images/1711532114phpfEGhVM.jpeg",
    "MCA_2024-2026/Hackaton/pasted images/image-15.webp",
    "MCA_2024-2026/Hackaton/pasted images/PIC16F877A-Microcontroller.png",
    "MCA_2024-2026/Hackaton/pasted images/PIC16F877A INPUT PIN CCT.png",
    "MCA_2024-2026/Hackaton/pasted images/8d2330b2-dfad-4bb6-a7c1-af103cd0ccd1.jpg",
    "MCA_2024-2026/Pasted image 20241011092607.png",
    "MCA_2024-2026/Untitled.canvas"
  ]
}